iias_project_cli/__init__.py
iias_project_cli/__main__.py
iias_project_cli/templates.py
iias_project_cli-1.0.6.dist-info/METADATA
iias_project_cli-1.0.6.dist-info/WHEEL
iias_project_cli-1.0.6.dist-info/entry_points.txt
iias_project_cli-1.0.6.dist-info/top_level.txt
iias_project_cli-1.0.6.dist-info/RECORD
