Metadata-Version: 2.1
Name: iias-project-cli
Version: 1.0.6
Summary: A commandline interface for creating project structures
Author: Jules Debeaumont
